hw4/mux_4_1.sv
module mux_4_1(d0, d1, d2, d3, s, y);
    
input logic d0, d1, d2, d3;
input logic [1:0] s;
output logic y;

assign y  =  s[1] ? (s[0] ? d3 : d2) :(s[0] ? d1 : d0);

endmodule

hw4/test_mux_4_1.sv
module test_mux_4_1;

logic d0, d1, d2, d3;
logic [1:0] s; 
wire y;

mux_4_1 UUT(.d0(d0), .d1(d1), .d2(d2), .d3(d3), .s(s), .y(y));

initial begin
  $dumpvars(0, UUT);
  $dumpfile("mux_4_1.vcd");

  $display("s d0 d1 d2 d3 | y");
  for (int i = 0; i < 64; i = i + 1) begin
    s[1] = i[5];
    s[0] = i[4];
    d3 = i[3];
    d2 = i[2];
    d1 = i[1];
    d0 = i[0];

    #1 $display("%b %b%b%b%b | %b", s, d0, d1, d2, d3, y);
  end
end


endmodule

hw4/dump.vcd
$date
	Sat Oct 16 22:42:48 2021
$end
$version
	Icarus Verilog
$end
$timescale
	1s
$end
$scope module test_mux_4_1 $end
$scope module UUT $end
$var wire 1 ! d0 $end
$var wire 1 " d1 $end
$var wire 1 # d2 $end
$var wire 1 $ d3 $end
$var wire 2 % s [1:0] $end
$var wire 1 & y $end
$upscope $end
$upscope $end
$enddefinitions $end
#0
$dumpvars
0&
b0 %
0$
0#
0"
0!
$end
#1
1&
1!
#2
0&
0!
1"
#3
1&
1!
#4
0&
0!
0"
1#
#5
1&
1!
#6
0&
0!
1"
#7
1&
1!
#8
0&
0!
0"
0#
1$
#9
1&
1!
#10
0&
0!
1"
#11
1&
1!
#12
0&
0!
0"
1#
#13
1&
1!
#14
0&
0!
1"
#15
1&
1!
#16
0&
0!
0"
0#
0$
b1 %
#17
1!
#18
1&
0!
1"
#19
1!
#20
0&
0!
0"
1#
#21
1!
#22
1&
0!
1"
#23
1!
#24
0&
0!
0"
0#
1$
#25
1!
#26
1&
0!
1"
#27
1!
#28
0&
0!
0"
1#
#29
1!
#30
1&
0!
1"
#31
1!
#32
0&
0!
0"
0#
0$
b10 %
#33
1!
#34
0!
1"
#35
1!
#36
1&
0!
0"
1#
#37
1!
#38
0!
1"
#39
1!
#40
0&
0!
0"
0#
1$
#41
1!
#42
0!
1"
#43
1!
#44
1&
0!
0"
1#
#45
1!
#46
0!
1"
#47
1!
#48
0&
0!
0"
0#
0$
b11 %
#49
1!
#50
0!
1"
#51
1!
#52
0!
0"
1#
#53
1!
#54
0!
1"
#55
1!
#56
1&
0!
0"
0#
1$
#57
1!
#58
0!
1"
#59
1!
#60
0!
0"
1#
#61
1!
#62
0!
1"
#63
1!
